Workbook
Name _1summ: #REF!
Name _2summ: #REF!
Name _3detail: #REF!
Name _92HEADCOUNT: #REF!
Name _93HEADCOUNT: #REF!
Name \P: #REF!
Name a: #REF!
Name aa: #REF!
Name acquisitions: #REF!
Name ADAPTA: #REF!
Name assets: #REF!
Name balsheet: #REF!
Name BORDER: #REF!
Name carolyn: #REF!
Name CASH: #REF!
Name compare: #REF!
Name days: #REF!
Name DiasCategorias: #REF!
Name EXPLAIN: #REF!
Name FechaInicio: #REF!
Name HEADING: #REF!
Name inter_co: #REF!
Name longtermdebt: #REF!
Name mo_je: #REF!
Name page\x2dtotal: #REF!
Name page\x2dtotal\x2dmaster0: #REF!
Name PAGE1: #REF!
Name PAGE10: #REF!
Name PAGE11: #REF!
Name PAGE2: #REF!
Name PAGE3: #REF!
Name PAGE4: #REF!
Name PAGE5: #REF!
Name PAGE6: #REF!
Name PAGE7: #REF!
Name PAGE8: #REF!
Name PAGE9: #REF!
Name recon_act: #REF!
Name REPORT1: #REF!
Name REPORT2: #REF!
Name REPORT3: #REF!
Name ROYALTY: #REF!
Name sasas: #REF!
Name SCALING: #REF!
Name SDFDF: #REF!
Name seyrtrt: #REF!

Sheet >>>>>>
A11: MI ZAPATO, SA DE CV
A14: VALUACIÓN

Sheet Presupuesto Anual
D1: MI ZAPATO, S.A. DE C.V.
D2: Estado de Resultados Proyectados del 1 de enero al 31 de diciembre, 2026
R4: 0.3 | S4: 0.25 | T4: 0.2 | U4: 0.15
D5: MES 1 | E5: MES 2 | F5: MES 3 | G5: MES 4 | H5: MES 5 | I5: MES 6 | J5: MES 7 | K5: MES 8 | L5: MES 9 | M5: MES 10 | N5: MES 11 | O5: MES 12 | Q5: AÑO 1 | R5: AÑO 2 | S5: AÑO 3 | T5: AÑO 4 | U5: AÑO 5
B7: Modelo 1 (40%) | C7: 0.4 | D7: =D11*$C$7 -> 0 | E7: =E11*$C$7 -> 10 | F7: =F11*$C$7 -> 10 | G7: =G11*$C$7 -> 10 | H7: =H11*$C$7 -> 20 | I7: =I11*$C$7 -> 30 | J7: =J11*$C$7 -> 30 | K7: =K11*$C$7 -> 50 | ... O7: =O11*$C$7 -> 60 | Q7: =SUM(C7:P7) -> 420.4 | R7: =Q7*(1+$R$4) -> 546.52 | S7: =R7*(1+$S$4) -> 683.15 | T7: =S7*(1+$T$4) -> 819.78 | U7: =T7*(1+$U$4) -> 942.747
B8: Modelo 2 (30%) | C8: 0.3 | D8: =D11*$C$8 -> 0 | E8: =E11*$C$8 -> 7.5 | F8: =F11*$C$8 -> 7.5 | G8: =G11*$C$8 -> 7.5 | H8: =H11*$C$8 -> 15 | I8: =I11*$C$8 -> 22.5 | J8: =J11*$C$8 -> 22.5 | K8: =K11*$C$8 -> 37.5 | ... O8: =O11*$C$8 -> 45 | Q8: =SUM(C8:P8) -> 315.3 | R8: =Q8*(1+$R$4) -> 409.89 | S8: =R8*(1+$S$4) -> 512.3625 | T8: =S8*(1+$T$4) -> 614.835 | U8: =T8*(1+$U$4) -> 707.06025
B9: Modelo 3 (20%) | C9: 0.2 | D9: =D11*$C$9 -> 0 | E9: =E11*$C$9 -> 5 | F9: =F11*$C$9 -> 5 | G9: =G11*$C$9 -> 5 | H9: =H11*$C$9 -> 10 | I9: =I11*$C$9 -> 15 | J9: =J11*$C$9 -> 15 | K9: =K11*$C$9 -> 25 | ... O9: =O11*$C$9 -> 30 | Q9: =SUM(C9:P9) -> 210.2 | R9: =Q9*(1+$R$4) -> 273.26 | S9: =R9*(1+$S$4) -> 341.575 | T9: =S9*(1+$T$4) -> 409.89 | U9: =T9*(1+$U$4) -> 471.3735
B10: Modelo 4 (10%) | C10: 0.1 | D10: =D11*$C$10 -> 0 | E10: =E11*$C$10 -> 2.5 | F10: =F11*$C$10 -> 2.5 | G10: =G11*$C$10 -> 2.5 | H10: =H11*$C$10 -> 5 | I10: =I11*$C$10 -> 7.5 | J10: =J11*$C$10 -> 7.5 | K10: =K11*$C$10 -> 12.5 | ... O10: =O11*$C$10 -> 15 | Q10: =SUM(C10:P10) -> 105.1 | R10: =Q10*(1+$R$4) -> 136.63 | S10: =R10*(1+$S$4) -> 170.7875 | T10: =S10*(1+$T$4) -> 204.945 | U10: =T10*(1+$U$4) -> 235.68675
B11: Unidades | D11: 0 | E11: 25 | F11: 25 | G11: 25 | H11: 50 | I11: 75 | J11: 75 | K11: 125 | L11: 150 | M11: 150 | N11: 200 | O11: 150 | Q11: =SUM(Q7:Q10) -> 1051 | R11: =SUM(R7:R10) -> 1366.3 | S11: =SUM(S7:S10) -> 1707.875 | T11: =SUM(T7:T10) -> 2049.45 | U11: =SUM(U7:U10) -> 2356.8675
B13: Modelo 1 (40%) | D13: =D7*Pricing!$P$3 -> 0 | E13: =E7*Pricing!$P$3 -> 35000 | F13: =F7*Pricing!$P$3 -> 35000 | G13: =G7*Pricing!$P$3 -> 35000 | H13: =H7*Pricing!$P$3 -> 70000 | I13: =I7*Pricing!$P$3 -> 105000 | J13: =J7*Pricing!$P$3 -> 105000 | K13: =K7*Pricing!$P$3 -> 175000 | ... O13: =O7*Pricing!$P$3 -> 210000 | Q13: =SUM(D13:O13) -> 1470000 | R13: =R7*Pricing!$P$3 -> 1912820 | S13: =S7*Pricing!$P$3 -> 2391025 | T13: =T7*Pricing!$P$3 -> 2869230 | U13: =U7*Pricing!$P$3 -> 3299614.5
B14: Modelo 2 (30%) | D14: =D8*Pricing!$P$4 -> 0 | E14: =E8*Pricing!$P$4 -> 26250 | F14: =F8*Pricing!$P$4 -> 26250 | G14: =G8*Pricing!$P$4 -> 26250 | H14: =H8*Pricing!$P$4 -> 52500 | I14: =I8*Pricing!$P$4 -> 78750 | J14: =J8*Pricing!$P$4 -> 78750 | K14: =K8*Pricing!$P$4 -> 131250 | ... O14: =O8*Pricing!$P$4 -> 157500 | Q14: =SUM(D14:O14) -> 1102500 | R14: =R8*Pricing!$P$4 -> 1434615 | S14: =S8*Pricing!$P$4 -> 1793268.8 | T14: =T8*Pricing!$P$4 -> 2151922.5 | U14: =U8*Pricing!$P$4 -> 2474710.9
B15: Modelo 3 (20%) | D15: =Pricing!$P$5*'Presupuesto Anual'!D9 -> 0 | E15: =Pricing!$P$5*'Presupuesto Anual'!E9 -> 20000 | F15: =Pricing!$P$5*'Presupuesto Anual'!F9 -> 20000 | G15: =Pricing!$P$5*'Presupuesto Anual'!G9 -> 20000 | H15: =Pricing!$P$5*'Presupuesto Anual'!H9 -> 40000 | I15: =Pricing!$P$5*'Presupuesto Anual'!I9 -> 60000 | J15: =Pricing!$P$5*'Presupuesto Anual'!J9 -> 60000 | K15: =Pricing!$P$5*'Presupuesto Anual'!K9 -> 100000 | ... O15: =Pricing!$P$5*'Presupuesto Anual'!O9 -> 120000 | Q15: =SUM(D15:O15) -> 840000 | R15: =Pricing!$P$5*'Presupuesto Anual'!R9 -> 1093040 | S15: =Pricing!$P$5*'Presupuesto Anual'!S9 -> 1366300 | T15: =Pricing!$P$5*'Presupuesto Anual'!T9 -> 1639560 | U15: =Pricing!$P$5*'Presupuesto Anual'!U9 -> 1885494
B16: Modelo 4 (10%) | D16: =Pricing!$P$6*'Presupuesto Anual'!D10 -> 0 | E16: =Pricing!$P$6*'Presupuesto Anual'!E10 -> 11250 | F16: =Pricing!$P$6*'Presupuesto Anual'!F10 -> 11250 | G16: =Pricing!$P$6*'Presupuesto Anual'!G10 -> 11250 | H16: =Pricing!$P$6*'Presupuesto Anual'!H10 -> 22500 | I16: =Pricing!$P$6*'Presupuesto Anual'!I10 -> 33750 | J16: =Pricing!$P$6*'Presupuesto Anual'!J10 -> 33750 | K16: =Pricing!$P$6*'Presupuesto Anual'!K10 -> 56250 | ... O16: =Pricing!$P$6*'Presupuesto Anual'!O10 -> 67500 | Q16: =SUM(D16:O16) -> 472500 | R16: =Pricing!$P$6*'Presupuesto Anual'!R10 -> 614835 | S16: =Pricing!$P$6*'Presupuesto Anual'!S10 -> 768543.75 | T16: =Pricing!$P$6*'Presupuesto Anual'!T10 -> 922252.5 | U16: =Pricing!$P$6*'Presupuesto Anual'!U10 -> 1060590.4
B18: Ventas | D18: =SUM(D13:D17) -> 0 | E18: =SUM(E13:E17) -> 92500 | F18: =SUM(F13:F17) -> 92500 | G18: =SUM(G13:G17) -> 92500 | H18: =SUM(H13:H17) -> 185000 | I18: =SUM(I13:I17) -> 277500 | J18: =SUM(J13:J17) -> 277500 | K18: =SUM(K13:K17) -> 462500 | ... O18: =SUM(O13:O17) -> 555000 | Q18: =SUM(Q13:Q17) -> 3885000 | R18: =SUM(R13:R17) -> 5055310 | S18: =SUM(S13:S17) -> 6319137.5 | T18: =SUM(T13:T17) -> 7582965 | U18: =SUM(U13:U17) -> 8720409.8
B19: Crecimiento vs. Período Anterior | E19: =IFERROR(E18/D18-1,"") | F19: =F18/E18-1 -> 0 | G19: =G18/F18-1 -> 0 | H19: =H18/G18-1 -> 1 | I19: =I18/H18-1 -> 0.5 | J19: =J18/I18-1 -> 0 | K19: =K18/J18-1 -> 0.66666667 | L19: =L18/K18-1 -> 0.2 | M19: =M18/L18-1 -> 0 | ... O19: =O18/N18-1 -> -0.25 | R19: =R18/Q18-1 -> 0.3012381 | S19: =S18/R18-1 -> 0.25 | T19: =T18/S18-1 -> 0.2 | U19: =U18/T18-1 -> 0.15
B21: COSTOS
B23: Piel tipo 1 | D23: =D7*Costeo!$J$52 -> 0 | E23: =E7*Costeo!$J$52 -> 825 | F23: =F7*Costeo!$J$52 -> 825 | G23: =G7*Costeo!$J$52 -> 825 | H23: =H7*Costeo!$J$52 -> 1650 | I23: =I7*Costeo!$J$52 -> 2475 | J23: =J7*Costeo!$J$52 -> 2475 | K23: =K7*Costeo!$J$52 -> 4125 | ... O23: =O7*Costeo!$J$52 -> 4950 | Q23: =SUM(D23:O23) -> 34650 | R23: =Q23*(1+R$4)*(1+SUPUESTOS!$D$6) -> 46621.575 | S23: =R23*(1+S$4)*(1+SUPUESTOS!$D$6) -> 60316.663 | T23: =S23*(1+T$4)*(1+SUPUESTOS!$D$6) -> 74913.295 | U23: =T23*(1+U$4)*(1+SUPUESTOS!$D$6) -> 89165.549
B24: Piel tipo 2 | D24: =D8*Costeo!$J$53 -> 0 | E24: =E8*Costeo!$J$53 -> 816.75 | F24: =F8*Costeo!$J$53 -> 816.75 | G24: =G8*Costeo!$J$53 -> 816.75 | H24: =H8*Costeo!$J$53 -> 1633.5 | I24: =I8*Costeo!$J$53 -> 2450.25 | J24: =J8*Costeo!$J$53 -> 2450.25 | K24: =K8*Costeo!$J$53 -> 4083.75 | ... O24: =O8*Costeo!$J$53 -> 4900.5 | Q24: =SUM(D24:O24) -> 34303.5 | R24: =Q24*(1+R$4)*(1+SUPUESTOS!$D$6) -> 46155.359 | S24: =R24*(1+S$4)*(1+SUPUESTOS!$D$6) -> 59713.496 | T24: =S24*(1+T$4)*(1+SUPUESTOS!$D$6) -> 74164.162 | U24: =T24*(1+U$4)*(1+SUPUESTOS!$D$6) -> 88273.894
B25: Piel tipo 3 | D25: =D9*Costeo!$J$54 -> 0 | E25: =E9*Costeo!$J$54 -> 965.25 | F25: =F9*Costeo!$J$54 -> 965.25 | G25: =G9*Costeo!$J$54 -> 965.25 | H25: =H9*Costeo!$J$54 -> 1930.5 | I25: =I9*Costeo!$J$54 -> 2895.75 | J25: =J9*Costeo!$J$54 -> 2895.75 | K25: =K9*Costeo!$J$54 -> 4826.25 | ... O25: =O9*Costeo!$J$54 -> 5791.5 | Q25: =SUM(D25:O25) -> 40540.5 | R25: =Q25*(1+R$4)*(1+SUPUESTOS!$D$6) -> 54547.243 | S25: =R25*(1+S$4)*(1+SUPUESTOS!$D$6) -> 70570.495 | T25: =S25*(1+T$4)*(1+SUPUESTOS!$D$6) -> 87648.555 | U25: =T25*(1+U$4)*(1+SUPUESTOS!$D$6) -> 104323.69
B26: Piel tipo 4 | D26: =D10*Costeo!$J$55 -> 0 | E26: =E10*Costeo!$J$55 -> 783.75 | F26: =F10*Costeo!$J$55 -> 783.75 | G26: =G10*Costeo!$J$55 -> 783.75 | H26: =H10*Costeo!$J$55 -> 1567.5 | I26: =I10*Costeo!$J$55 -> 2351.25 | J26: =J10*Costeo!$J$55 -> 2351.25 | K26: =K10*Costeo!$J$55 -> 3918.75 | ... O26: =O10*Costeo!$J$55 -> 4702.5 | Q26: =SUM(D26:O26) -> 32917.5 | R26: =Q26*(1+R$4)*(1+SUPUESTOS!$D$6) -> 44290.496 | S26: =R26*(1+S$4)*(1+SUPUESTOS!$D$6) -> 57300.83 | T26: =S26*(1+T$4)*(1+SUPUESTOS!$D$6) -> 71167.63 | U26: =T26*(1+U$4)*(1+SUPUESTOS!$D$6) -> 84707.272
B27: Suela Piel | D27: =D11*Costeo!$J$56 -> 0 | E27: =E11*Costeo!$J$56 -> 250 | F27: =F11*Costeo!$J$56 -> 250 | G27: =G11*Costeo!$J$56 -> 250 | H27: =H11*Costeo!$J$56 -> 500 | I27: =I11*Costeo!$J$56 -> 750 | J27: =J11*Costeo!$J$56 -> 750 | K27: =K11*Costeo!$J$56 -> 1250 | ... O27: =O11*Costeo!$J$56 -> 1500 | Q27: =SUM(D27:O27) -> 10500 | R27: =Q27*(1+R$4)*(1+SUPUESTOS!$D$6) -> 14127.75 | S27: =R27*(1+S$4)*(1+SUPUESTOS!$D$6) -> 18277.777 | T27: =S27*(1+T$4)*(1+SUPUESTOS!$D$6) -> 22700.998 | U27: =T27*(1+U$4)*(1+SUPUESTOS!$D$6) -> 27019.863
B28: Suela Madera | D28: =D11*Costeo!$J$57 -> 0 | E28: =E11*Costeo!$J$57 -> 495 | F28: =F11*Costeo!$J$57 -> 495 | G28: =G11*Costeo!$J$57 -> 495 | H28: =H11*Costeo!$J$57 -> 990 | I28: =I11*Costeo!$J$57 -> 1485 | J28: =J11*Costeo!$J$57 -> 1485 | K28: =K11*Costeo!$J$57 -> 2475 | ... O28: =O11*Costeo!$J$57 -> 2970 | Q28: =SUM(D28:O28) -> 20790 | R28: =Q28*(1+R$4)*(1+SUPUESTOS!$D$6) -> 27972.945 | S28: =R28*(1+S$4)*(1+SUPUESTOS!$D$6) -> 36189.998 | T28: =S28*(1+T$4)*(1+SUPUESTOS!$D$6) -> 44947.977 | U28: =T28*(1+U$4)*(1+SUPUESTOS!$D$6) -> 53499.33
B29: Pegamento | D29: =D11*Costeo!$J$58 -> 0 | E29: =E11*Costeo!$J$58 -> 11.25 | F29: =F11*Costeo!$J$58 -> 11.25 | G29: =G11*Costeo!$J$58 -> 11.25 | H29: =H11*Costeo!$J$58 -> 22.5 | I29: =I11*Costeo!$J$58 -> 33.75 | J29: =J11*Costeo!$J$58 -> 33.75 | K29: =K11*Costeo!$J$58 -> 56.25 | ... O29: =O11*Costeo!$J$58 -> 67.5 | Q29: =SUM(D29:O29) -> 472.5 | R29: =Q29*(1+R$4)*(1+SUPUESTOS!$D$6) -> 635.74875 | S29: =R29*(1+S$4)*(1+SUPUESTOS!$D$6) -> 822.49995 | T29: =S29*(1+T$4)*(1+SUPUESTOS!$D$6) -> 1021.5449 | U29: =T29*(1+U$4)*(1+SUPUESTOS!$D$6) -> 1215.8939
B30: Agujetas | D30: =D11*Costeo!$J$59 -> 0 | E30: =E11*Costeo!$J$59 -> 150 | F30: =F11*Costeo!$J$59 -> 150 | G30: =G11*Costeo!$J$59 -> 150 | H30: =H11*Costeo!$J$59 -> 300 | I30: =I11*Costeo!$J$59 -> 450 | J30: =J11*Costeo!$J$59 -> 450 | K30: =K11*Costeo!$J$59 -> 750 | ... O30: =O11*Costeo!$J$59 -> 900 | Q30: =SUM(D30:O30) -> 6300 | R30: =Q30*(1+R$4)*(1+SUPUESTOS!$D$6) -> 8476.65 | S30: =R30*(1+S$4)*(1+SUPUESTOS!$D$6) -> 10966.666 | T30: =S30*(1+T$4)*(1+SUPUESTOS!$D$6) -> 13620.599 | U30: =T30*(1+U$4)*(1+SUPUESTOS!$D$6) -> 16211.918
B31: Hilo | D31: =D11*Costeo!$J$60 -> 0 | E31: =E11*Costeo!$J$60 -> 0.025 | F31: =F11*Costeo!$J$60 -> 0.025 | G31: =G11*Costeo!$J$60 -> 0.025 | H31: =H11*Costeo!$J$60 -> 0.05 | I31: =I11*Costeo!$J$60 -> 0.075 | J31: =J11*Costeo!$J$60 -> 0.075 | K31: =K11*Costeo!$J$60 -> 0.125 | ... O31: =O11*Costeo!$J$60 -> 0.15 | Q31: =SUM(D31:O31) -> 1.05 | R31: =Q31*(1+R$4)*(1+SUPUESTOS!$D$6) -> 1.412775 | S31: =R31*(1+S$4)*(1+SUPUESTOS!$D$6) -> 1.8277777 | T31: =S31*(1+T$4)*(1+SUPUESTOS!$D$6) -> 2.2700998 | U31: =T31*(1+U$4)*(1+SUPUESTOS!$D$6) -> 2.7019863
B32: Técnico 1 | D32: 10000 | E32: =D32 -> 10000 | F32: =E32 -> 10000 | G32: =F32 -> 10000 | H32: =G32 -> 10000 | I32: =H32 -> 10000 | J32: =I32 -> 10000 | K32: =J32 -> 10000 | L32: =K32 -> 10000 | ... O32: =N32 -> 10000 | Q32: =SUM(D32:O32) -> 120000 | R32: =Q32*(1+R$4)*(1+SUPUESTOS!$D$6) -> 161460 | S32: =R32*(1+S$4)*(1+SUPUESTOS!$D$6) -> 208888.87 | T32: =S32*(1+T$4)*(1+SUPUESTOS!$D$6) -> 259439.98 | U32: =T32*(1+U$4)*(1+SUPUESTOS!$D$6) -> 308798.44
B33: Técnico 2 | D33: 10000 | E33: =D33 -> 10000 | F33: =E33 -> 10000 | G33: =F33 -> 10000 | H33: =G33 -> 10000 | I33: =H33 -> 10000 | J33: =I33 -> 10000 | K33: =J33 -> 10000 | L33: =K33 -> 10000 | ... O33: =N33 -> 10000 | Q33: =SUM(D33:O33) -> 120000 | R33: =Q33*(1+R$4)*(1+SUPUESTOS!$D$6) -> 161460 | S33: =R33*(1+S$4)*(1+SUPUESTOS!$D$6) -> 208888.87 | T33: =S33*(1+T$4)*(1+SUPUESTOS!$D$6) -> 259439.98 | U33: =T33*(1+U$4)*(1+SUPUESTOS!$D$6) -> 308798.44
B34: Técnico 3 | D34: 12000 | E34: =D34 -> 12000 | F34: =E34 -> 12000 | G34: =F34 -> 12000 | H34: =G34 -> 12000 | I34: =H34 -> 12000 | J34: =I34 -> 12000 | K34: =J34 -> 12000 | L34: =K34 -> 12000 | ... O34: =N34 -> 12000 | Q34: =SUM(D34:O34) -> 144000 | R34: =Q34*(1+R$4)*(1+SUPUESTOS!$D$6) -> 193752 | S34: =R34*(1+S$4)*(1+SUPUESTOS!$D$6) -> 250666.65 | T34: =S34*(1+T$4)*(1+SUPUESTOS!$D$6) -> 311327.98 | U34: =T34*(1+U$4)*(1+SUPUESTOS!$D$6) -> 370558.13
B35: Técnico 4 | D35: 15000 | E35: =D35 -> 15000 | F35: =E35 -> 15000 | G35: =F35 -> 15000 | H35: =G35 -> 15000 | I35: =H35 -> 15000 | J35: =I35 -> 15000 | K35: =J35 -> 15000 | L35: =K35 -> 15000 | ... O35: =N35 -> 15000 | Q35: =SUM(D35:O35) -> 180000 | R35: =Q35*(1+R$4)*(1+SUPUESTOS!$D$6) -> 242190 | S35: =R35*(1+S$4)*(1+SUPUESTOS!$D$6) -> 313333.31 | T35: =S35*(1+T$4)*(1+SUPUESTOS!$D$6) -> 389159.97 | U35: =T35*(1+U$4)*(1+SUPUESTOS!$D$6) -> 463197.66
B36: Energía Eléctrica | E36: 3500 | G36: 3500 | I36: 3500 | K36: 3500 | M36: 3500 | O36: 3500 | Q36: =SUM(D36:O36) -> 21000 | R36: =Q36*(1+R$4)*(1+SUPUESTOS!$D$6) -> 28255.5 | S36: =R36*(1+S$4)*(1+SUPUESTOS!$D$6) -> 36555.553 | T36: =S36*(1+T$4)*(1+SUPUESTOS!$D$6) -> 45401.997 | U36: =T36*(1+U$4)*(1+SUPUESTOS!$D$6) -> 54039.727
B38: Total Costos Variables | D38: =SUM(D23:D37) -> 47000 | E38: =SUM(E23:E37) -> 54797.025 | F38: =SUM(F23:F37) -> 51297.025 | G38: =SUM(G23:G37) -> 54797.025 | H38: =SUM(H23:H37) -> 55594.05 | I38: =SUM(I23:I37) -> 63391.075 | J38: =SUM(J23:J37) -> 59891.075 | K38: =SUM(K23:K37) -> 71985.125 | ... O38: =SUM(O23:O37) -> 76282.15 | Q38: =SUM(Q23:Q37) -> 765475.05 | R38: =SUM(R23:R37) -> 1029946.7 | S38: =SUM(S23:S37) -> 1332493.5 | T38: =SUM(T23:T37) -> 1654956.9 | U38: =SUM(U23:U37) -> 1969812.5
B39: % sobre las ventas | D39: =IFERROR(D38/D18,"") | E39: =E38/E18 -> 0.59240027 | F39: =F38/F18 -> 0.55456243 | G39: =G38/G18 -> 0.59240027 | H39: =H38/H18 -> 0.30050838 | I39: =I38/I18 -> 0.22843631 | J39: =J38/J18 -> 0.21582369 | K39: =K38/K18 -> 0.15564351 | L39: =L38/L18 -> 0.13113901 | ... O39: =O38/O18 -> 0.13744532 | Q39: =Q38/Q18 -> 0.19703347 | R39: =R38/R18 -> 0.20373561 | S39: =S38/S18 -> 0.21086636 | T39: =T38/T18 -> 0.21824668 | U39: =U38/U18 -> 0.22588532
B41: Utilidad Bruta | D41: =D18-D38 -> -47000 | E41: =E18-E38 -> 37702.975 | F41: =F18-F38 -> 41202.975 | G41: =G18-G38 -> 37702.975 | H41: =H18-H38 -> 129405.95 | I41: =I18-I38 -> 214108.92 | J41: =J18-J38 -> 217608.92 | K41: =K18-K38 -> 390514.88 | ... O41: =O18-O38 -> 478717.85 | Q41: =Q18-Q38 -> 3119525 | R41: =R18-R38 -> 4025363.3 | S41: =S18-S38 -> 4986644 | T41: =T18-T38 -> 5928008.1 | U41: =U18-U38 -> 6750597.2
B42: % sobre las ventas | D42: =IFERROR(D41/D18,"") | E42: =E41/E18 -> 0.40759973 | F42: =F41/F18 -> 0.44543757 | G42: =G41/G18 -> 0.40759973 | H42: =H41/H18 -> 0.69949162 | I42: =I41/I18 -> 0.77156369 | J42: =J41/J18 -> 0.78417631 | K42: =K41/K18 -> 0.84435649 | L42: =L41/L18 -> 0.86886099 | ... O42: =O41/O18 -> 0.86255468 | Q42: =Q41/Q18 -> 0.80296653 | R42: =R41/R18 -> 0.79626439 | S42: =S41/S18 -> 0.78913364 | T42: =T41/T18 -> 0.78175332 | U42: =U41/U18 -> 0.77411468
B44: GASTOS
B46: GASTOS ADMINISTRATIVOS | D46: =Gastos!C11 -> 125000 | E46: =D46 -> 125000 | F46: =E46 -> 125000 | G46: =F46 -> 125000 | H46: =G46 -> 125000 | I46: =H46 -> 125000 | J46: =I46 -> 125000 | K46: =J46 -> 125000 | L46: =K46 -> 125000 | ... O46: =N46 -> 125000 | Q46: =SUM(D46:O46) -> 1500000 | R46: =Q46*(1+SUPUESTOS!$D$6) -> 1552500 | S46: =(Gastos!D11*12)*(1+SUPUESTOS!$D$6) -> 3974400 | T46: =S46*(1+SUPUESTOS!$D$6) -> 4113504 | U46: =T46*(1+SUPUESTOS!$D$6) -> 4257476.6
B48: GASTOS OPERATIVOS | D48: =Gastos!C21 -> 34400 | E48: =D48 -> 34400 | F48: =E48 -> 34400 | G48: =F48 -> 34400 | H48: =G48 -> 34400 | I48: =H48 -> 34400 | J48: =I48 -> 34400 | K48: =J48 -> 34400 | L48: =K48 -> 34400 | ... O48: =N48 -> 34400 | Q48: =SUM(D48:O48) -> 412800 | R48: =Q48*(1+SUPUESTOS!$D$6) -> 427248 | S48: =(Gastos!D21*12)*(1+SUPUESTOS!$D$6) -> 731538 | T48: =S48*(1+SUPUESTOS!$D$6) -> 757141.83 | U48: =T48*(1+SUPUESTOS!$D$6) -> 783641.79
B50: GASTOS DE VENTA
B51: Bolsas | D51: =Gastos!$C$29*'Presupuesto Anual'!D11 -> 0 | E51: =Gastos!$C$29*'Presupuesto Anual'!E11 -> 87.5 | F51: =Gastos!$C$29*'Presupuesto Anual'!F11 -> 87.5 | G51: =Gastos!$C$29*'Presupuesto Anual'!G11 -> 87.5 | H51: =Gastos!$C$29*'Presupuesto Anual'!H11 -> 175 | I51: =Gastos!$C$29*'Presupuesto Anual'!I11 -> 262.5 | J51: =Gastos!$C$29*'Presupuesto Anual'!J11 -> 262.5 | K51: =Gastos!$C$29*'Presupuesto Anual'!K11 -> 437.5 | ... O51: =Gastos!$C$29*'Presupuesto Anual'!O11 -> 525 | Q51: =SUM(D51:O51) -> 3675 | R51: =Q51*(1+SUPUESTOS!$D$6) -> 3803.625 | S51: =R51*(1+SUPUESTOS!$D$6) -> 3936.7519 | T51: =S51*(1+SUPUESTOS!$D$6) -> 4074.5382 | U51: =T51*(1+SUPUESTOS!$D$6) -> 4217.147
B52: Cajas | D52: =Gastos!$C$32*'Presupuesto Anual'!D11 -> 0 | E52: =Gastos!$C$32*'Presupuesto Anual'!E11 -> 300 | F52: =Gastos!$C$32*'Presupuesto Anual'!F11 -> 300 | G52: =Gastos!$C$32*'Presupuesto Anual'!G11 -> 300 | H52: =Gastos!$C$32*'Presupuesto Anual'!H11 -> 600 | I52: =Gastos!$C$32*'Presupuesto Anual'!I11 -> 900 | J52: =Gastos!$C$32*'Presupuesto Anual'!J11 -> 900 | K52: =Gastos!$C$32*'Presupuesto Anual'!K11 -> 1500 | ... O52: =Gastos!$C$32*'Presupuesto Anual'!O11 -> 1800 | Q52: =SUM(D52:O52) -> 12600 | R52: =Q52*(1+SUPUESTOS!$D$6) -> 13041 | S52: =R52*(1+SUPUESTOS!$D$6) -> 13497.435 | T52: =S52*(1+SUPUESTOS!$D$6) -> 13969.845 | U52: =T52*(1+SUPUESTOS!$D$6) -> 14458.79
B53: Promoción Redes Sociales | D53: =Gastos!C26 -> 25000 | E53: =D53 -> 25000 | F53: =E53 -> 25000 | G53: =F53 -> 25000 | H53: =G53 -> 25000 | I53: =H53 -> 25000 | J53: =I53 -> 25000 | K53: =J53 -> 25000 | L53: =K53 -> 25000 | ... O53: =N53 -> 25000 | Q53: =SUM(D53:O53) -> 300000 | R53: =Q53*(1+SUPUESTOS!$D$6) -> 310500 | S53: =R53*(1+SUPUESTOS!$D$6) -> 321367.5 | T53: =S53*(1+SUPUESTOS!$D$6) -> 332615.36 | U53: =T53*(1+SUPUESTOS!$D$6) -> 344256.9
B55: Total Gastos Fijos | D55: =SUM(D46:D54) -> 184400 | E55: =SUM(E46:E54) -> 184787.5 | F55: =SUM(F46:F54) -> 184787.5 | G55: =SUM(G46:G54) -> 184787.5 | H55: =SUM(H46:H54) -> 185175 | I55: =SUM(I46:I54) -> 185562.5 | J55: =SUM(J46:J54) -> 185562.5 | K55: =SUM(K46:K54) -> 186337.5 | ... O55: =SUM(O46:O54) -> 186725 | Q55: =SUM(Q46:Q54) -> 2229075 | R55: =SUM(R46:R54) -> 2307092.6 | S55: =SUM(S46:S54) -> 5044739.7 | T55: =SUM(T46:T54) -> 5221305.6 | U55: =SUM(U46:U54) -> 5404051.3
B56: % sobre las ventas | D56: =IFERROR(D55/D18,"") | E56: =E55/E18 -> 1.9977027 | F56: =F55/F18 -> 1.9977027 | G56: =G55/G18 -> 1.9977027 | H56: =H55/H18 -> 1.0009459 | I56: =I55/I18 -> 0.66869369 | J56: =J55/J18 -> 0.66869369 | K56: =K55/K18 -> 0.40289189 | L56: =L55/L18 -> 0.33644144 | ... O56: =O55/O18 -> 0.33644144 | Q56: =Q55/Q18 -> 0.57376448 | R56: =R55/R18 -> 0.45637016 | S56: =S55/S18 -> 0.79832725 | T56: =T55/T18 -> 0.68855726 | U56: =U55/U18 -> 0.61970153
B58: Depreciación Máquina 1 | D58: =Gastos!H37 -> 1166.6667 | E58: =D58 -> 1166.6667 | F58: =E58 -> 1166.6667 | G58: =F58 -> 1166.6667 | H58: =G58 -> 1166.6667 | I58: =H58 -> 1166.6667 | J58: =I58 -> 1166.6667 | K58: =J58 -> 1166.6667 | L58: =K58 -> 1166.6667 | ... O58: =N58 -> 1166.6667 | Q58: =SUM(D58:O58) -> 14000 | R58: =Gastos!$F$37 -> 14000 | S58: =R58 -> 14000 | T58: =S58 -> 14000 | U58: =T58 -> 14000
B59: Depreciación Máquina 2 | D59: 0 | E59: =D59 -> 0 | F59: =E59 -> 0 | G59: =F59 -> 0 | H59: =Gastos!H38 -> 1166.6667 | I59: =H59 -> 1166.6667 | J59: =I59 -> 1166.6667 | K59: =J59 -> 1166.6667 | L59: =K59 -> 1166.6667 | M59: =L59 -> 1166.6667 | N59: =M59 -> 1166.6667 | O59: =N59 -> 1166.6667 | Q59: =SUM(D59:O59) -> 9333.3333 | R59: =Gastos!$F$38 -> 14000 | S59: =R59 -> 14000 | T59: =S59 -> 14000 | U59: =T59 -> 14000
B60: Depreciación Máquina 3 | D60: 0 | E60: 0 | F60: =E60 -> 0 | G60: =Gastos!H41 -> 1058.3333 | H60: =G60 -> 1058.3333 | I60: =H60 -> 1058.3333 | J60: =I60 -> 1058.3333 | K60: =J60 -> 1058.3333 | L60: =K60 -> 1058.3333 | M60: =L60 -> 1058.3333 | N60: =M60 -> 1058.3333 | O60: =N60 -> 1058.3333 | Q60: =SUM(D60:O60) -> 9525 | R60: =Gastos!$F$41 -> 12700 | S60: =R60 -> 12700 | T60: =S60 -> 12700 | U60: =T60 -> 12700
B62: Total Depreciaciones | D62: =SUM(D58:D61) -> 1166.6667 | E62: =SUM(E58:E61) -> 1166.6667 | F62: =SUM(F58:F61) -> 1166.6667 | G62: =SUM(G58:G61) -> 2225 | H62: =SUM(H58:H61) -> 3391.6667 | I62: =SUM(I58:I61) -> 3391.6667 | J62: =SUM(J58:J61) -> 3391.6667 | K62: =SUM(K58:K61) -> 3391.6667 | ... O62: =SUM(O58:O61) -> 3391.6667 | Q62: =SUM(Q58:Q61) -> 32858.333 | R62: =SUM(R58:R61) -> 40700 | S62: =SUM(S58:S61) -> 40700 | T62: =SUM(T58:T61) -> 40700 | U62: =SUM(U58:U61) -> 40700
B64: Amortización Inversión 1 | D64: =Gastos!H45 -> 2916.6667 | E64: =D64 -> 2916.6667 | F64: =E64 -> 2916.6667 | G64: =F64 -> 2916.6667 | H64: =G64 -> 2916.6667 | I64: =H64 -> 2916.6667 | J64: =I64 -> 2916.6667 | K64: =J64 -> 2916.6667 | L64: =K64 -> 2916.6667 | ... O64: =N64 -> 2916.6667 | Q64: =SUM(D64:O64) -> 35000
B65: Amortización Inversión 2 | D65: =Gastos!H48 -> 5416.6667 | E65: =D65 -> 5416.6667 | F65: =E65 -> 5416.6667 | G65: =F65 -> 5416.6667 | H65: =G65 -> 5416.6667 | I65: =H65 -> 5416.6667 | J65: =I65 -> 5416.6667 | K65: =J65 -> 5416.6667 | L65: =K65 -> 5416.6667 | ... O65: =N65 -> 5416.6667 | Q65: =SUM(D65:O65) -> 65000
B67: Total Amortizaciones | D67: =SUM(D64:D66) -> 8333.3333 | E67: =SUM(E64:E66) -> 8333.3333 | F67: =SUM(F64:F66) -> 8333.3333 | G67: =SUM(G64:G66) -> 8333.3333 | H67: =SUM(H64:H66) -> 8333.3333 | I67: =SUM(I64:I66) -> 8333.3333 | J67: =SUM(J64:J66) -> 8333.3333 | K67: =SUM(K64:K66) -> 8333.3333 | ... O67: =SUM(O64:O66) -> 8333.3333 | Q67: =SUM(Q64:Q66) -> 100000 | R67: =SUM(R64:R66) -> 0 | S67: =SUM(S64:S66) -> 0 | T67: =SUM(T64:T66) -> 0 | U67: =SUM(U64:U66) -> 0
B69: Utilidad de Operación | D69: =D41-D55-D62-D67 -> -240900 | E69: =E41-E55-E62-E67 -> -156584.52 | F69: =F41-F55-F62-F67 -> -153084.52 | G69: =G41-G55-G62-G67 -> -157642.86 | H69: =H41-H55-H62-H67 -> -67494.05 | I69: =I41-I55-I62-I67 -> 16821.425 | J69: =J41-J55-J62-J67 -> 20321.425 | K69: =K41-K55-K62-K67 -> 192452.38 | ... O69: =O41-O55-O62-O67 -> 280267.85 | Q69: =Q41-Q55-Q62-Q67 -> 757591.62 | R69: =R41-R55-R62-R67 -> 1677570.7 | S69: =S41-S55-S62-S67 -> -98795.704 | T69: =T41-T55-T62-T67 -> 666002.48 | U69: =U41-U55-U62-U67 -> 1305846
B70: % sobre las ventas | D70: =IFERROR(D69/D18,"") | E70: =E69/E18 -> -1.6928057 | F70: =F69/F18 -> -1.6549678 | G70: =G69/G18 -> -1.7042471 | H70: =H69/H18 -> -0.3648327 | I70: =I69/I18 -> 0.060617748 | J70: =J69/J18 -> 0.07323036 | K70: =K69/K18 -> 0.41611324 | L70: =L69/L18 -> 0.51129342 | ... O70: =O69/O18 -> 0.50498712 | Q70: =Q69/Q18 -> 0.19500428 | R70: =R69/R18 -> 0.33184329 | S70: =S69/S18 -> -0.015634365 | T70: =T69/T18 -> 0.087828768 | U70: =U69/U18 -> 0.14974594
B72: Préstamo Bancario | D72: ='Crédito Bancario'!C12 -> 6250 | E72: ='Crédito Bancario'!C13 -> 6076.3889 | F72: ='Crédito Bancario'!C14 -> 5902.7778 | G72: ='Crédito Bancario'!C15 -> 5729.1667 | H72: ='Crédito Bancario'!C16 -> 5555.5556 | I72: ='Crédito Bancario'!C17 -> 5381.9444 | J72: ='Crédito Bancario'!C18 -> 5208.3333 | K72: ='Crédito Bancario'!C19 -> 5034.7222 | L72: ='Crédito Bancario'!C20 -> 4861.1111 | M72: ='Crédito Bancario'!C21 -> 4687.5 | N72: ='Crédito Bancario'!C22 -> 4513.8889 | O72: ='Crédito Bancario'!C23 -> 4340.2778 | Q72: =SUM(D72:O72) -> 63541.667 | R72: ='Crédito Bancario'!H35 -> 38541.667 | S72: ='Crédito Bancario'!H47 -> 13541.667 | T72: ='Crédito Bancario'!H59 -> -11458.333 | U72: ='Crédito Bancario'!H71 -> -36458.333
B74: Total Gasto Financiero | D74: =SUM(D72:D73) -> 6250 | E74: =SUM(E72:E73) -> 6076.3889 | F74: =SUM(F72:F73) -> 5902.7778 | G74: =SUM(G72:G73) -> 5729.1667 | H74: =SUM(H72:H73) -> 5555.5556 | I74: =SUM(I72:I73) -> 5381.9444 | J74: =SUM(J72:J73) -> 5208.3333 | K74: =SUM(K72:K73) -> 5034.7222 | ... O74: =SUM(O72:O73) -> 4340.2778 | Q74: =SUM(Q72:Q73) -> 63541.667 | R74: =SUM(R72:R73) -> 38541.667 | S74: =SUM(S72:S73) -> 13541.667 | T74: =SUM(T72:T73) -> -11458.333 | U74: =SUM(U72:U73) -> -36458.333
B76: Utilidad Antes de Impuestos | D76: =D69-D74 -> -247150 | E76: =E69-E74 -> -162660.91 | F76: =F69-F74 -> -158987.3 | G76: =G69-G74 -> -163372.02 | H76: =H69-H74 -> -73049.606 | I76: =I69-I74 -> 11439.481 | J76: =J69-J74 -> 15113.092 | K76: =K69-K74 -> 187417.65 | ... O76: =O69-O74 -> 275927.57 | Q76: =Q69-Q74 -> 694049.95 | R76: =R69-R74 -> 1639029 | S76: =S69-S74 -> -112337.37 | T76: =T69-T74 -> 677460.81 | U76: =U69-U74 -> 1342304.3
B77: % sobre las ventas | D77: =IFERROR(D76/D18,"") | E77: =E76/E18 -> -1.7584964 | F77: =F76/F18 -> -1.7187817 | G77: =G76/G18 -> -1.7661841 | H77: =H76/H18 -> -0.39486273 | I77: =I76/I18 -> 0.041223353 | J77: =J76/J18 -> 0.054461592 | K77: =K76/K18 -> 0.40522736 | L77: =L76/L18 -> 0.50253466 | ... O77: =O76/O18 -> 0.4971668 | Q77: =Q76/Q18 -> 0.17864864 | R77: =R76/R18 -> 0.32421929 | S77: =S76/S18 -> -0.017777326 | T77: =T76/T18 -> 0.089339831 | U77: =U76/U18 -> 0.15392675
B79: Pago ISR + PTU | D79: =IF(D76<0,0,D76*(SUPUESTOS!$D$3+SUPUESTOS!$D$4)) -> 0 | E79: =IF(E76<0,0,E76*(SUPUESTOS!$D$3+SUPUESTOS!$D$4)) -> 0 | F79: =IF(F76<0,0,F76*(SUPUESTOS!$D$3+SUPUESTOS!$D$4)) -> 0 | G79: =IF(G76<0,0,G76*(SUPUESTOS!$D$3+SUPUESTOS!$D$4)) -> 0 | H79: =IF(H76<0,0,H76*(SUPUESTOS!$D$3+SUPUESTOS!$D$4)) -> 0 | I79: =IF(I76<0,0,I76*(SUPUESTOS!$D$3+SUPUESTOS!$D$4)) -> 4575.7922 | J79: =IF(J76<0,0,J76*(SUPUESTOS!$D$3+SUPUESTOS!$D$4)) -> 6045.2367 | K79: =IF(K76<0,0,K76*(SUPUESTOS!$D$3+SUPUESTOS!$D$4)) -> 74967.061 | ... O79: =IF(O76<0,0,O76*(SUPUESTOS!$D$3+SUPUESTOS!$D$4)) -> 110371.03 | Q79: =SUM(D79:O79) -> 599707.92 | R79: =IF(R76<0,0,R76*(SUPUESTOS!$D$3+SUPUESTOS!$D$4)) -> 655611.61 | S79: =IF(S76<0,0,S76*(SUPUESTOS!$D$3+SUPUESTOS!$D$4)) -> 0 | T79: =IF(T76<0,0,T76*(SUPUESTOS!$D$3+SUPUESTOS!$D$4)) -> 270984.32 | U79: =IF(U76<0,0,U76*(SUPUESTOS!$D$3+SUPUESTOS!$D$4)) -> 536921.72
B80: IMSS | D80: 0 | E80: 850 | F80: 850 | G80: 850 | H80: 850 | I80: 850 | J80: 850 | K80: 850 | L80: 850 | M80: 850 | N80: 850 | O80: 850 | Q80: =SUM(D80:O80) -> 9350 | R80: =Q80 -> 9350 | S80: =R80 -> 9350 | T80: =S80 -> 9350 | U80: =T80 -> 9350
B81: INFONAVIT | D81: 0 | E81: 0 | F81: 0 | G81: 0 | H81: 0 | I81: 0 | J81: 0 | K81: 0 | L81: 0 | M81: 0 | N81: 0 | O81: 0 | Q81: =SUM(D81:O81) -> 0 | R81: =SUM(E81:Q81) -> 0 | S81: =SUM(F81:R81) -> 0 | T81: =SUM(G81:S81) -> 0 | U81: =SUM(H81:T81) -> 0
B82: Otros | D82: 0 | E82: 0 | F82: 0 | G82: 0 | H82: 0 | I82: 0 | J82: 0 | K82: 0 | L82: 0 | M82: 0 | N82: 0 | O82: 0 | Q82: =SUM(D82:O82) -> 0 | R82: =SUM(E82:Q82) -> 0 | S82: =SUM(F82:R82) -> 0 | T82: =SUM(G82:S82) -> 0 | U82: =SUM(H82:T82) -> 0
B84: Total Impuestos | D84: =SUM(D79:D83) -> 0 | E84: =SUM(E79:E83) -> 850 | F84: =SUM(F79:F83) -> 850 | G84: =SUM(G79:G83) -> 850 | H84: =SUM(H79:H83) -> 850 | I84: =SUM(I79:I83) -> 5425.7922 | J84: =SUM(J79:J83) -> 6895.2367 | K84: =SUM(K79:K83) -> 75817.061 | ... O84: =SUM(O79:O83) -> 111221.03 | Q84: =SUM(Q79:Q83) -> 609057.92 | R84: =SUM(R79:R83) -> 664961.61 | S84: =SUM(S79:S83) -> 9350 | T84: =SUM(T79:T83) -> 280334.32 | U84: =SUM(U79:U83) -> 546271.72
B86: UTILIDAD NETA | D86: =D76-D84 -> -247150 | E86: =E76-E84 -> -163510.91 | F86: =F76-F84 -> -159837.3 | G86: =G76-G84 -> -164222.02 | H86: =H76-H84 -> -73899.606 | I86: =I76-I84 -> 6013.6883 | J86: =J76-J84 -> 8217.855 | K86: =K76-K84 -> 111600.59 | ... O86: =O76-O84 -> 164706.54 | Q86: =SUM(D86:O86) -> 84992.031 | R86: =R76-R84 -> 974067.42 | S86: =S76-S84 -> -121687.37 | T86: =T76-T84 -> 397126.49 | U86: =U76-U84 -> 796032.58
B87: % sobre las ventas | D87: =IFERROR(D86/D18,"") | E87: =E86/E18 -> -1.7676856 | F87: =F86/F18 -> -1.7279708 | G87: =G86/G18 -> -1.7753732 | H87: =H86/H18 -> -0.39945733 | I87: =I86/I18 -> 0.021670949 | J87: =J86/J18 -> 0.029613892 | K87: =K86/K18 -> 0.24129858 | L87: =L86/L18 -> 0.29998927 | ... O87: =O86/O18 -> 0.29676855 | Q87: =Q86/Q18 -> 0.021876971 | R87: =R86/R18 -> 0.19268203 | S87: =S86/S18 -> -0.019256959 | T87: =T86/T18 -> 0.052370872 | U87: =U86/U18 -> 0.091283851
B89: Utilidad Acumulada | D89: =D86 -> -247150 | E89: =D89+E86 -> -410660.91 | F89: =E89+F86 -> -570498.22 | G89: =F89+G86 -> -734720.24 | H89: =G89+H86 -> -808619.85 | I89: =H89+I86 -> -802606.16 | J89: =I89+J86 -> -794388.3 | K89: =J89+K86 -> -682787.71 | L89: =K89+L86 -> -516293.67 | ... O89: =N89+O86 -> 84992.031 | Q89: =O89 -> 84992.031 | R89: =Q89+R86 -> 1059059.4 | S89: =R89+S86 -> 937372.08 | T89: =S89+T86 -> 1334498.6 | U89: =T89+U86 -> 2130531.1
B91: EBITDA | D91: =D69+D62+D67 -> -231400 | E91: =E69+E62+E67 -> -147084.52 | F91: =F69+F62+F67 -> -143584.52 | G91: =G69+G62+G67 -> -147084.52 | H91: =H69+H62+H67 -> -55769.05 | I91: =I69+I62+I67 -> 28546.425 | J91: =J69+J62+J67 -> 32046.425 | K91: =K69+K62+K67 -> 204177.38 | ... O91: =O69+O62+O67 -> 291992.85 | Q91: =SUM(D91:O91) -> 890449.95 | R91: =R69+R62+R67 -> 1718270.7 | S91: =S69+S62+S67 -> -58095.704 | T91: =T69+T62+T67 -> 706702.48 | U91: =U69+U62+U67 -> 1346546
B92: % sobre las ventas | D92: =IFERROR(D91/D18,"") | E92: =E91/E18 -> -1.590103 | F92: =F91/F18 -> -1.5522651 | G92: =G91/G18 -> -1.590103 | H92: =H91/H18 -> -0.30145432 | I92: =I91/I18 -> 0.10287 | J92: =J91/J18 -> 0.11548261 | K92: =K91/K18 -> 0.44146459 | L92: =L91/L18 -> 0.53241955 | ... O92: =O91/O18 -> 0.52611324 | Q92: =Q91/Q18 -> 0.22920205 | R92: =R91/R18 -> 0.33989423 | S92: =S91/S18 -> -0.0091936129 | T92: =T91/T18 -> 0.093196062 | U92: =U91/U18 -> 0.15441315

Sheet Costeo
C1: LISTA DE MATERIALES | F1: Costo Unitario
A3: MODELO 1 | B3: Piel tipo 1 | D3: 0.33 | E3: metros | F3: =Costeo!J52 -> 82.5
B4: Suela Piel | D4: 0.02 | E4: metros | F4: =Costeo!J56 -> 10
B5: Suela Madera | D5: 2 | E5: pzas | F5: =Costeo!J57 -> 19.8
B6: Pegamento | D6: 0.005 | E6: lt | F6: =Costeo!J58 -> 0.45
B7: Agujetas | D7: 2 | E7: pzas | F7: =Costeo!J59 -> 6
B8: Hilo | D8: 0.001 | E8: metros | F8: =Costeo!J60 -> 0.001 | H8: =SUM(F3:F8) -> 118.751
B10: Técnico 1 | D10: 4 | E10: hrs | F10: =Costeo!J62 -> 285.44244
F12: =SUM(F3:F11) -> 404.19344 | G12: COSTO ESTÁNDAR SIN ABSORCIÓN DE GASTO
A15: MODELO 2 | B15: Piel tipo 2 | D15: 0.33 | E15: metros | F15: =Costeo!J53 -> 108.9
B16: Suela Piel | D16: 0.02 | E16: metros | F16: =Costeo!J56 -> 10
B17: Suela Madera | D17: 2 | E17: pzas | F17: =Costeo!J57 -> 19.8
B18: Pegamento | D18: 0.005 | E18: lt | F18: =Costeo!J58 -> 0.45
B19: Agujetas | D19: 2 | E19: pzas | F19: =Costeo!J59 -> 6
B20: Hilo | D20: 0.001 | E20: metros | F20: =Costeo!J60 -> 0.001
B22: Técnico 2 | D22: 4 | E22: hrs | F22: =Costeo!J63 -> 285.44244
F24: =SUM(F15:F23) -> 430.59344 | G24: COSTO ESTÁNDAR SIN ABSORCIÓN DE GASTO
A27: MODELO 3 | B27: Piel tipo 3 | D27: 0.33 | E27: metros | F27: =Costeo!J54 -> 193.05
B28: Suela Piel | D28: 0.02 | E28: metros | F28: =Costeo!J56 -> 10
B29: Suela Madera | D29: 2 | E29: pzas | F29: =Costeo!J57 -> 19.8
B30: Pegamento | D30: 0.005 | E30: lt | F30: =Costeo!J58 -> 0.45
B31: Agujetas | D31: 2 | E31: pzas | F31: =Costeo!J59 -> 6
B32: Hilo | D32: 0.001 | E32: metros | F32: =Costeo!J60 -> 0.001
B34: Técnico 3 | D34: 4 | E34: hrs | F34: =Costeo!J64 -> 342.53092
F36: =SUM(F27:F35) -> 571.83192 | G36: COSTO ESTÁNDAR SIN ABSORCIÓN DE GASTO
A39: MODELO 4 | B39: Piel tipo 4 | D39: 0.33 | E39: metros | F39: =Costeo!J55 -> 313.5
B40: Suela Piel | D40: 0.02 | E40: metros | F40: =Costeo!J56 -> 10
B41: Suela Madera | D41: 2 | E41: pzas | F41: =Costeo!J57 -> 19.8
B42: Pegamento | D42: 0.005 | E42: lt | F42: =Costeo!J58 -> 0.45
B43: Agujetas | D43: 2 | E43: pzas | F43: =Costeo!J59 -> 6
B44: Hilo | D44: 0.001 | E44: metros | F44: =Costeo!J60 -> 0.001
B46: Técnico 4 | D46: 4 | E46: hrs | F46: =Costeo!J65 -> 428.16365
F48: =SUM(F39:F47) -> 777.91465 | G48: COSTO ESTÁNDAR SIN ABSORCIÓN DE GASTO
B51: ITEM | D51: Costo Total | F51: Volumen | H51: Volumen por pieza | J51: Costo Unitario | L51: # Piezas
A52: MAT. PRIMA | B52: Piel tipo 1 | D52: 2500 | F52: 10 | G52: m | H52: 0.33 | J52: =(D52/F52)*H52 -> 82.5 | L52: =F52/H52 -> 30.30303
B53: Piel tipo 2 | D53: 3300 | F53: 10 | G53: m | H53: 0.33 | J53: =(D53/F53)*H53 -> 108.9 | L53: =F53/H53 -> 30.30303
B54: Piel tipo 3 | D54: 5850 | F54: 10 | G54: m | H54: 0.33 | J54: =(D54/F54)*H54 -> 193.05 | L54: =F54/H54 -> 30.30303
B55: Piel tipo 4 | D55: 9500 | F55: 10 | G55: m | H55: 0.33 | J55: =(D55/F55)*H55 -> 313.5 | L55: =F55/H55 -> 30.30303
B56: Suela Piel | D56: 2500 | F56: 5 | G56: m | H56: 0.02 | J56: =(D56/F56)*H56 -> 10 | L56: =F56/H56 -> 250
B57: Suela Madera | D57: 990 | F57: 100 | G57: p | H57: 2 | J57: =(D57/F57)*H57 -> 19.8 | L57: =F57/H57 -> 50
B58: Pegamento | D58: 900 | F58: 10 | G58: l | H58: 0.005 | J58: =(D58/F58)*H58 -> 0.45 | L58: =F58/H58 -> 2000
B59: Agujetas | D59: 300 | F59: 100 | G59: p | H59: 2 | J59: =(D59/F59)*H59 -> 6 | L59: =F59/H59 -> 50
B60: Hilo | D60: 100 | F60: 100 | G60: m | H60: 0.001 | J60: =(D60/F60)*H60 -> 0.001 | L60: =F60/H60 -> 100000
L61: Total Horas | M61: Hr x pza | N61: Pzas x Tec
A62: MANO DE OBRA | B62: Técnico 1 | D62: ='Presupuesto Anual'!D32*12 -> 120000 | F62: 1 | G62: pax | H62: ='Presupuesto Anual'!Q7 -> 420.4 | J62: =D62/$H$62 -> 285.44244 | L62: =((8*5)*4)*12 -> 1920 | M62: =Costeo!D10 -> 4 | N62: =L62/M62 -> 480 | O62: =N62/12 -> 40
B63: Técnico 2 | D63: ='Presupuesto Anual'!D33*12 -> 120000 | F63: 1 | G63: pax | J63: =D63/$H$62 -> 285.44244 | L63: =((8*5)*4)*12 -> 1920 | M63: =M62 -> 4 | N63: ='Presupuesto Anual'!Q8 -> 315.3 | O63: =N63/12 -> 26.275
B64: Técnico 3 | D64: ='Presupuesto Anual'!D34*12 -> 144000 | F64: 1 | G64: pax | J64: =D64/$H$62 -> 342.53092 | L64: =((8*5)*4)*12 -> 1920 | M64: =M62 -> 4 | N64: ='Presupuesto Anual'!Q9 -> 210.2 | O64: =N64/12 -> 17.516667
B65: Técnico 4 | D65: ='Presupuesto Anual'!D35*12 -> 180000 | F65: 1 | G65: pax | J65: =D65/$H$62 -> 428.16365 | L65: =((8*5)*4)*12 -> 1920 | M65: =M63 -> 4 | N65: ='Presupuesto Anual'!Q10 -> 105.1 | O65: =N65/12 -> 8.7583333
M66: Cap. Instalada: | N66: =SUM(N62:N65) -> 1110.6 | O66: pzas.
B67: Energía Eléctrica | D67: 3500 | F67: 1 | G67: bim | H67: =H62 -> 420.4 | J67: =D67/H67 -> 8.3254044 | M67: Venta proyectada: | N67: ='Presupuesto Anual'!Q11 -> 1051
M68: Diferencia: | N68: =N66-N67 -> 59.6 | O68: =N68/N66 -> 0.053664686
J69: =SUM(J52:J68) -> 2084.1059

Sheet Gastos
B1: ESTRUCTURA DE GASTOS
B4: GASTO ADMINISTRATIVO
C5: AÑO 1-2 | D5: AÑO 3
B6: CEO - PARTNER | C6: 50000 | D6: 120000
B7: CMO - PARTNER | C7: 35000 | D7: 100000
B8: DISEÑO | C8: 15000 | D8: 40000
B9: GTE DE PLANTA | C9: 25000 | D9: 40000
B10: ASISTENTE | D10: 20000
C11: =SUM(C6:C10) -> 125000 | D11: =SUM(D6:D10) -> 320000
B13: GASTO OPERATIVO
C15: AÑO 1-2 | D15: AÑO 3
B16: RENTA OFICINA | C16: 20500 | D16: 35000 | E16: Cambio de oficinas
B17: GASTOS DE OPERACIÓN | C17: 5000 | D17: 10000
B18: GASTO ADMON. / CONTAB. | C18: 7000 | D18: 7000
B19: ARRENDAMIENTO COMPUTADORAS | C19: 1900 | D19: 1900
B20: OTROS GASTOS DE PRODUCCIÓN | C20: 0 | D20: 5000
C21: =SUM(C16:C20) -> 34400 | D21: =SUM(D16:D20) -> 58900
B24: GASTO VENTA
C25: AÑO 1 | D25: AÑO 3
B26: MKT / SOCIAL MEDIA | C26: 25000 | D26: 40000
B28: BOLSAS | C28: Gasto Total
B29: Costo por Pieza | C29: 3.5
B31: CAJA | C31: Gasto Total
B32: Costo por Pieza | C32: 12
J35: DEPRECIACIÓN EN AÑOS
B36: MÁQUINA SINGER M-1000 | D36: Inversión | F36: Depr Anual | H36: Depr Mes | J36: Computadoras | K36: 3
B37: M1 | D37: 140000 | F37: =D37/K39 -> 14000 | H37: =F37/12 -> 1166.6667 | J37: Autos | K37: 5
B38: M2 | D38: 140000 | F38: =D38/K39 -> 14000 | H38: =F38/12 -> 1166.6667 | J38: Muebles | K38: 10
J39: Máquinas | K39: 10
B40: MÁQUINA SIYO 9000 | D40: Gasto Total
B41: M3 | D41: 127000 | F41: =D41/K39 -> 12700 | H41: =F41/12 -> 1058.3333
B44: ACONDICIONAR TALLER | D44: Inversión | H44: Amort Mes
D45: 35000 | H45: =D45/12 -> 2916.6667
B47: ACONDICIONAMIENTO OFICINAS | D47: Gasto Total
D48: 65000 | H48: =D48/12 -> 5416.6667

Sheet Pricing
D2: Costo Unitario (MP & MOD) | F2: Absorción Gasto | H2: % de Gasto vs Costo | J2: COSTO UNITARIO ESTÁNDAR | L2: Margen Esperado | N2: Precio de Venta | P2: Redondeo
B3: =Costeo!A3 -> MODELO 1 | D3: =Costeo!F12 -> 404.19344 | F3: =$H$14 -> 2120.9087 | H3: =D3/F3 -> 0.1905756 | J3: =D3+F3 -> 2525.1021 | L3: 0.15 | N3: =J3*(1+L3) -> 2903.8674 | P3: 3500
B4: =Costeo!A15 -> MODELO 2 | D4: =Costeo!F24 -> 430.59344 | F4: =$H$14 -> 2120.9087 | H4: =F4/D4-1 -> 3.9255481 | J4: =D4+F4 -> 2551.5021 | L4: 0.15 | N4: =J4*(1+L4) -> 2934.2274 | P4: 3500
B5: =Costeo!A27 -> MODELO 3 | D5: =Costeo!F36 -> 571.83192 | F5: =$H$14 -> 2120.9087 | H5: =F5/D5-1 -> 2.7089721 | J5: =D5+F5 -> 2692.7406 | L5: 0.2 | N5: =J5*(1+L5) -> 3231.2887 | P5: 4000
B6: =Costeo!A39 -> MODELO 4 | D6: =Costeo!F48 -> 777.91465 | F6: =$H$14 -> 2120.9087 | H6: =F6/D6-1 -> 1.7264028 | J6: =D6+F6 -> 2898.8233 | L6: 0.25 | N6: =J6*(1+L6) -> 3623.5291 | P6: 4500
D9: Gasto Total | F9: Volumen estimado de Venta (pzas) | H9: Absorción por pieza
B10: GASTO ADMINISTRATIVO | D10: ='Presupuesto Anual'!Q46 -> 1500000 | F10: ='Presupuesto Anual'!Q11 -> 1051 | H10: =D10/$F$10 -> 1427.2122
B11: ='Presupuesto Anual'!B48 -> GASTOS OPERATIVOS | D11: ='Presupuesto Anual'!Q48 -> 412800 | H11: =D11/$F$10 -> 392.76879
B12: GASTO DE VENTA | D12: ='Presupuesto Anual'!Q51+'Presupuesto Anual'!Q52+'Presupuesto Anual'!Q53 -> 316275 | H12: =D12/$F$10 -> 300.92769
B14: Total Gastos | D14: =SUM(D10:D13) -> 2229075 | H14: =SUM(H10:H13) -> 2120.9087

Sheet Gráficas

Sheet Crédito Bancario
C1: TABLA DE AMORTIZACIÓN FINANCIERA A SALDOS INSOLUTOS
C3: MONTO | D3: 500000
C4: TASA ANUAL TOTAL | D4: 0.15
C5: TASA MENSUAL | D5: =D4/12 -> 0.0125
C6: PLAZO MENSUAL | D6: =D7*12 -> 36
C7: PLAZO (en años) | D7: 3
C8: CAPITAL A AMORTIZAR | D8: =D3/D6 -> 13888.889
A10: Año | B10: Período | C10: Interes | D10: Capital | E10: Pago mensual DECRECIENTE | F10: Saldo pendiente | G10: Pago año presupuesto | H10: Pago año INTERESES
B11: 0 | F11: =D3 -> 500000
B12: 1 | C12: =F11*$D$5 -> 6250 | D12: =D8 -> 13888.889 | E12: =C12+D12 -> 20138.889 | F12: =$F$11-D12 -> 486111.11
B13: 2 | C13: =F12*$D$5 -> 6076.3889 | D13: =D12 -> 13888.889 | E13: =C13+D13 -> 19965.278 | F13: =F12-D13 -> 472222.22
B14: 3 | C14: =F13*$D$5 -> 5902.7778 | D14: =D13 -> 13888.889 | E14: =C14+D14 -> 19791.667 | F14: =F13-D14 -> 458333.33
B15: 4 | C15: =F14*$D$5 -> 5729.1667 | D15: =D14 -> 13888.889 | E15: =C15+D15 -> 19618.056 | F15: =F14-D15 -> 444444.44
B16: 5 | C16: =F15*$D$5 -> 5555.5556 | D16: =D15 -> 13888.889 | E16: =C16+D16 -> 19444.444 | F16: =F15-D16 -> 430555.56
B17: 6 | C17: =F16*$D$5 -> 5381.9444 | D17: =D16 -> 13888.889 | E17: =C17+D17 -> 19270.833 | F17: =F16-D17 -> 416666.67
B18: 7 | C18: =F17*$D$5 -> 5208.3333 | D18: =D17 -> 13888.889 | E18: =C18+D18 -> 19097.222 | F18: =F17-D18 -> 402777.78
B19: 8 | C19: =F18*$D$5 -> 5034.7222 | D19: =D18 -> 13888.889 | E19: =C19+D19 -> 18923.611 | F19: =F18-D19 -> 388888.89
B20: 9 | C20: =F19*$D$5 -> 4861.1111 | D20: =D19 -> 13888.889 | E20: =C20+D20 -> 18750 | F20: =F19-D20 -> 375000
B21: 10 | C21: =F20*$D$5 -> 4687.5 | D21: =D20 -> 13888.889 | E21: =C21+D21 -> 18576.389 | F21: =F20-D21 -> 361111.11
B22: 11 | C22: =F21*$D$5 -> 4513.8889 | D22: =D21 -> 13888.889 | E22: =C22+D22 -> 18402.778 | F22: =F21-D22 -> 347222.22
A23: 1 | B23: 12 | C23: =F22*$D$5 -> 4340.2778 | D23: =D22 -> 13888.889 | E23: =C23+D23 -> 18229.167 | F23: =F22-D23 -> 333333.33 | G23: =SUM(E12:E23) -> 230208.33 | H23: =SUM(C12:C23) -> 63541.667
B24: 13 | C24: =F23*$D$5 -> 4166.6667 | D24: =D23 -> 13888.889 | E24: =C24+D24 -> 18055.556 | F24: =F23-D24 -> 319444.44
B25: 14 | C25: =F24*$D$5 -> 3993.0556 | D25: =D24 -> 13888.889 | E25: =C25+D25 -> 17881.944 | F25: =F24-D25 -> 305555.56
B26: 15 | C26: =F25*$D$5 -> 3819.4444 | D26: =D25 -> 13888.889 | E26: =C26+D26 -> 17708.333 | F26: =F25-D26 -> 291666.67
B27: 16 | C27: =F26*$D$5 -> 3645.8333 | D27: =D26 -> 13888.889 | E27: =C27+D27 -> 17534.722 | F27: =F26-D27 -> 277777.78
B28: 17 | C28: =F27*$D$5 -> 3472.2222 | D28: =D27 -> 13888.889 | E28: =C28+D28 -> 17361.111 | F28: =F27-D28 -> 263888.89
B29: 18 | C29: =F28*$D$5 -> 3298.6111 | D29: =D28 -> 13888.889 | E29: =C29+D29 -> 17187.5 | F29: =F28-D29 -> 250000
B30: 19 | C30: =F29*$D$5 -> 3125 | D30: =D29 -> 13888.889 | E30: =C30+D30 -> 17013.889 | F30: =F29-D30 -> 236111.11
B31: 20 | C31: =F30*$D$5 -> 2951.3889 | D31: =D30 -> 13888.889 | E31: =C31+D31 -> 16840.278 | F31: =F30-D31 -> 222222.22
B32: 21 | C32: =F31*$D$5 -> 2777.7778 | D32: =D31 -> 13888.889 | E32: =C32+D32 -> 16666.667 | F32: =F31-D32 -> 208333.33
B33: 22 | C33: =F32*$D$5 -> 2604.1667 | D33: =D32 -> 13888.889 | E33: =C33+D33 -> 16493.056 | F33: =F32-D33 -> 194444.44
B34: 23 | C34: =F33*$D$5 -> 2430.5556 | D34: =D33 -> 13888.889 | E34: =C34+D34 -> 16319.444 | F34: =F33-D34 -> 180555.56
A35: 2 | B35: 24 | C35: =F34*$D$5 -> 2256.9444 | D35: =D34 -> 13888.889 | E35: =C35+D35 -> 16145.833 | F35: =F34-D35 -> 166666.67 | G35: =SUM(E24:E35) -> 205208.33 | H35: =SUM(C24:C35) -> 38541.667
B36: 25 | C36: =F35*$D$5 -> 2083.3333 | D36: =D35 -> 13888.889 | E36: =C36+D36 -> 15972.222 | F36: =F35-D36 -> 152777.78
B37: 26 | C37: =F36*$D$5 -> 1909.7222 | D37: =D36 -> 13888.889 | E37: =C37+D37 -> 15798.611 | F37: =F36-D37 -> 138888.89
B38: 27 | C38: =F37*$D$5 -> 1736.1111 | D38: =D37 -> 13888.889 | E38: =C38+D38 -> 15625 | F38: =F37-D38 -> 125000
B39: 28 | C39: =F38*$D$5 -> 1562.5 | D39: =D38 -> 13888.889 | E39: =C39+D39 -> 15451.389 | F39: =F38-D39 -> 111111.11
B40: 29 | C40: =F39*$D$5 -> 1388.8889 | D40: =D39 -> 13888.889 | E40: =C40+D40 -> 15277.778 | F40: =F39-D40 -> 97222.222
B41: 30 | C41: =F40*$D$5 -> 1215.2778 | D41: =D40 -> 13888.889 | E41: =C41+D41 -> 15104.167 | F41: =F40-D41 -> 83333.333
B42: 31 | C42: =F41*$D$5 -> 1041.6667 | D42: =D41 -> 13888.889 | E42: =C42+D42 -> 14930.556 | F42: =F41-D42 -> 69444.444
B43: 32 | C43: =F42*$D$5 -> 868.05556 | D43: =D42 -> 13888.889 | E43: =C43+D43 -> 14756.944 | F43: =F42-D43 -> 55555.556
B44: 33 | C44: =F43*$D$5 -> 694.44444 | D44: =D43 -> 13888.889 | E44: =C44+D44 -> 14583.333 | F44: =F43-D44 -> 41666.667
B45: 34 | C45: =F44*$D$5 -> 520.83333 | D45: =D44 -> 13888.889 | E45: =C45+D45 -> 14409.722 | F45: =F44-D45 -> 27777.778
B46: 35 | C46: =F45*$D$5 -> 347.22222 | D46: =D45 -> 13888.889 | E46: =C46+D46 -> 14236.111 | F46: =F45-D46 -> 13888.889
A47: 3 | B47: 36 | C47: =F46*$D$5 -> 173.61111 | D47: =D46 -> 13888.889 | E47: =C47+D47 -> 14062.5 | F47: =F46-D47 -> 3.2378011e-10 | G47: =SUM(E36:E47) -> 180208.33 | H47: =SUM(C36:C47) -> 13541.667
B48: 37 | C48: =F47*$D$5 -> 4.0472514e-12 | D48: =D47 -> 13888.889 | E48: =C48+D48 -> 13888.889 | F48: =F47-D48 -> -13888.889
B49: 38 | C49: =F48*$D$5 -> -173.61111 | D49: =D48 -> 13888.889 | E49: =C49+D49 -> 13715.278 | F49: =F48-D49 -> -27777.778
B50: 39 | C50: =F49*$D$5 -> -347.22222 | D50: =D49 -> 13888.889 | E50: =C50+D50 -> 13541.667 | F50: =F49-D50 -> -41666.667
B51: 40 | C51: =F50*$D$5 -> -520.83333 | D51: =D50 -> 13888.889 | E51: =C51+D51 -> 13368.056 | F51: =F50-D51 -> -55555.556
B52: 41 | C52: =F51*$D$5 -> -694.44444 | D52: =D51 -> 13888.889 | E52: =C52+D52 -> 13194.444 | F52: =F51-D52 -> -69444.444
B53: 42 | C53: =F52*$D$5 -> -868.05556 | D53: =D52 -> 13888.889 | E53: =C53+D53 -> 13020.833 | F53: =F52-D53 -> -83333.333
B54: 43 | C54: =F53*$D$5 -> -1041.6667 | D54: =D53 -> 13888.889 | E54: =C54+D54 -> 12847.222 | F54: =F53-D54 -> -97222.222
B55: 44 | C55: =F54*$D$5 -> -1215.2778 | D55: =D54 -> 13888.889 | E55: =C55+D55 -> 12673.611 | F55: =F54-D55 -> -111111.11
B56: 45 | C56: =F55*$D$5 -> -1388.8889 | D56: =D55 -> 13888.889 | E56: =C56+D56 -> 12500 | F56: =F55-D56 -> -125000
B57: 46 | C57: =F56*$D$5 -> -1562.5 | D57: =D56 -> 13888.889 | E57: =C57+D57 -> 12326.389 | F57: =F56-D57 -> -138888.89
B58: 47 | C58: =F57*$D$5 -> -1736.1111 | D58: =D57 -> 13888.889 | E58: =C58+D58 -> 12152.778 | F58: =F57-D58 -> -152777.78
A59: 4 | B59: 48 | C59: =F58*$D$5 -> -1909.7222 | D59: =D58 -> 13888.889 | E59: =C59+D59 -> 11979.167 | F59: =F58-D59 -> -166666.67 | G59: =SUM(E48:E59) -> 155208.33 | H59: =SUM(C48:C59) -> -11458.333
B60: 49 | C60: =F59*$D$5 -> -2083.3333 | D60: =D59 -> 13888.889 | E60: =C60+D60 -> 11805.556 | F60: =F59-D60 -> -180555.56
B61: 50 | C61: =F60*$D$5 -> -2256.9444 | D61: =D60 -> 13888.889 | E61: =C61+D61 -> 11631.944 | F61: =F60-D61 -> -194444.44
B62: 51 | C62: =F61*$D$5 -> -2430.5556 | D62: =D61 -> 13888.889 | E62: =C62+D62 -> 11458.333 | F62: =F61-D62 -> -208333.33
B63: 52 | C63: =F62*$D$5 -> -2604.1667 | D63: =D62 -> 13888.889 | E63: =C63+D63 -> 11284.722 | F63: =F62-D63 -> -222222.22
B64: 53 | C64: =F63*$D$5 -> -2777.7778 | D64: =D63 -> 13888.889 | E64: =C64+D64 -> 11111.111 | F64: =F63-D64 -> -236111.11
B65: 54 | C65: =F64*$D$5 -> -2951.3889 | D65: =D64 -> 13888.889 | E65: =C65+D65 -> 10937.5 | F65: =F64-D65 -> -250000
B66: 55 | C66: =F65*$D$5 -> -3125 | D66: =D65 -> 13888.889 | E66: =C66+D66 -> 10763.889 | F66: =F65-D66 -> -263888.89
B67: 56 | C67: =F66*$D$5 -> -3298.6111 | D67: =D66 -> 13888.889 | E67: =C67+D67 -> 10590.278 | F67: =F66-D67 -> -277777.78
B68: 57 | C68: =F67*$D$5 -> -3472.2222 | D68: =D67 -> 13888.889 | E68: =C68+D68 -> 10416.667 | F68: =F67-D68 -> -291666.67
B69: 58 | C69: =F68*$D$5 -> -3645.8333 | D69: =D68 -> 13888.889 | E69: =C69+D69 -> 10243.056 | F69: =F68-D69 -> -305555.56
B70: 59 | C70: =F69*$D$5 -> -3819.4444 | D70: =D69 -> 13888.889 | E70: =C70+D70 -> 10069.444 | F70: =F69-D70 -> -319444.44
A71: 5 | B71: 60 | C71: =F70*$D$5 -> -3993.0556 | D71: =D70 -> 13888.889 | E71: =C71+D71 -> 9895.8333 | F71: =F70-D71 -> -333333.33 | G71: =SUM(E60:E71) -> 130208.33 | H71: =SUM(C60:C71) -> -36458.333 | I71: =SUM(H11:H71) -> 67708.333
B72: =B71+1 -> 61 | C72: =F71*$D$5 -> -4166.6667 | D72: =D71 -> 13888.889 | E72: =C72+D72 -> 9722.2222 | F72: =$F$71-D72 -> -347222.22
B73: =B72+1 -> 62 | C73: =F72*$D$5 -> -4340.2778 | D73: =D72 -> 13888.889 | E73: =C73+D73 -> 9548.6111 | F73: =F72-D73 -> -361111.11
B74: =B73+1 -> 63 | C74: =F73*$D$5 -> -4513.8889 | D74: =D73 -> 13888.889 | E74: =C74+D74 -> 9375 | F74: =F73-D74 -> -375000
B75: =B74+1 -> 64 | C75: =F74*$D$5 -> -4687.5 | D75: =D74 -> 13888.889 | E75: =C75+D75 -> 9201.3889 | F75: =F74-D75 -> -388888.89
B76: =B75+1 -> 65 | C76: =F75*$D$5 -> -4861.1111 | D76: =D75 -> 13888.889 | E76: =C76+D76 -> 9027.7778 | F76: =F75-D76 -> -402777.78
B77: =B76+1 -> 66 | C77: =F76*$D$5 -> -5034.7222 | D77: =D76 -> 13888.889 | E77: =C77+D77 -> 8854.1667 | F77: =F76-D77 -> -416666.67
B78: =B77+1 -> 67 | C78: =F77*$D$5 -> -5208.3333 | D78: =D77 -> 13888.889 | E78: =C78+D78 -> 8680.5556 | F78: =F77-D78 -> -430555.56
B79: =B78+1 -> 68 | C79: =F78*$D$5 -> -5381.9444 | D79: =D78 -> 13888.889 | E79: =C79+D79 -> 8506.9444 | F79: =F78-D79 -> -444444.44
B80: =B79+1 -> 69 | C80: =F79*$D$5 -> -5555.5556 | D80: =D79 -> 13888.889 | E80: =C80+D80 -> 8333.3333 | F80: =F79-D80 -> -458333.33
B81: =B80+1 -> 70 | C81: =F80*$D$5 -> -5729.1667 | D81: =D80 -> 13888.889 | E81: =C81+D81 -> 8159.7222 | F81: =F80-D81 -> -472222.22
B82: =B81+1 -> 71 | C82: =F81*$D$5 -> -5902.7778 | D82: =D81 -> 13888.889 | E82: =C82+D82 -> 7986.1111 | F82: =F81-D82 -> -486111.11
A83: 6 | B83: =B82+1 -> 72 | C83: =F82*$D$5 -> -6076.3889 | D83: =D82 -> 13888.889 | E83: =C83+D83 -> 7812.5 | F83: =F82-D83 -> -500000
B84: =B83+1 -> 73 | C84: =F83*$D$5 -> -6250 | D84: =D83 -> 13888.889 | E84: =C84+D84 -> 7638.8889 | F84: =F83-D84 -> -513888.89
B85: =B84+1 -> 74 | C85: =F84*$D$5 -> -6423.6111 | D85: =D84 -> 13888.889 | E85: =C85+D85 -> 7465.2778 | F85: =F84-D85 -> -527777.78
B86: =B85+1 -> 75 | C86: =F85*$D$5 -> -6597.2222 | D86: =D85 -> 13888.889 | E86: =C86+D86 -> 7291.6667 | F86: =F85-D86 -> -541666.67
B87: =B86+1 -> 76 | C87: =F86*$D$5 -> -6770.8333 | D87: =D86 -> 13888.889 | E87: =C87+D87 -> 7118.0556 | F87: =F86-D87 -> -555555.56
B88: =B87+1 -> 77 | C88: =F87*$D$5 -> -6944.4444 | D88: =D87 -> 13888.889 | E88: =C88+D88 -> 6944.4444 | F88: =F87-D88 -> -569444.44
B89: =B88+1 -> 78 | C89: =F88*$D$5 -> -7118.0556 | D89: =D88 -> 13888.889 | E89: =C89+D89 -> 6770.8333 | F89: =F88-D89 -> -583333.33
B90: =B89+1 -> 79 | C90: =F89*$D$5 -> -7291.6667 | D90: =D89 -> 13888.889 | E90: =C90+D90 -> 6597.2222 | F90: =F89-D90 -> -597222.22
B91: =B90+1 -> 80 | C91: =F90*$D$5 -> -7465.2778 | D91: =D90 -> 13888.889 | E91: =C91+D91 -> 6423.6111 | F91: =F90-D91 -> -611111.11
B92: =B91+1 -> 81 | C92: =F91*$D$5 -> -7638.8889 | D92: =D91 -> 13888.889 | E92: =C92+D92 -> 6250 | F92: =F91-D92 -> -625000
B93: =B92+1 -> 82 | C93: =F92*$D$5 -> -7812.5 | D93: =D92 -> 13888.889 | E93: =C93+D93 -> 6076.3889 | F93: =F92-D93 -> -638888.89
B94: =B93+1 -> 83 | C94: =F93*$D$5 -> -7986.1111 | D94: =D93 -> 13888.889 | E94: =C94+D94 -> 5902.7778 | F94: =F93-D94 -> -652777.78
A95: 7 | B95: =B94+1 -> 84 | C95: =F94*$D$5 -> -8159.7222 | D95: =D94 -> 13888.889 | E95: =C95+D95 -> 5729.1667 | F95: =F94-D95 -> -666666.67
B96: =B95+1 -> 85 | C96: =F95*$D$5 -> -8333.3333 | D96: =D95 -> 13888.889 | E96: =C96+D96 -> 5555.5556 | F96: =F95-D96 -> -680555.56
B97: =B96+1 -> 86 | C97: =F96*$D$5 -> -8506.9444 | D97: =D96 -> 13888.889 | E97: =C97+D97 -> 5381.9444 | F97: =F96-D97 -> -694444.44
B98: =B97+1 -> 87 | C98: =F97*$D$5 -> -8680.5556 | D98: =D97 -> 13888.889 | E98: =C98+D98 -> 5208.3333 | F98: =F97-D98 -> -708333.33
B99: =B98+1 -> 88 | C99: =F98*$D$5 -> -8854.1667 | D99: =D98 -> 13888.889 | E99: =C99+D99 -> 5034.7222 | F99: =F98-D99 -> -722222.22
B100: =B99+1 -> 89 | C100: =F99*$D$5 -> -9027.7778 | D100: =D99 -> 13888.889 | E100: =C100+D100 -> 4861.1111 | F100: =F99-D100 -> -736111.11
B101: =B100+1 -> 90 | C101: =F100*$D$5 -> -9201.3889 | D101: =D100 -> 13888.889 | E101: =C101+D101 -> 4687.5 | F101: =F100-D101 -> -750000
B102: =B101+1 -> 91 | C102: =F101*$D$5 -> -9375 | D102: =D101 -> 13888.889 | E102: =C102+D102 -> 4513.8889 | F102: =F101-D102 -> -763888.89
...

Sheet RENTABILIDAD DE LA INVERSION
B2: ANÁLISIS DE RENTABILIDAD DEL NEGOCIO
B4: INVERSIÓN TOTAL | E4: =MIN('Presupuesto Anual'!D89:O89,'Presupuesto Anual'!R89,'Presupuesto Anual'!S89,'Presupuesto Anual'!T89,'Presupuesto Anual'!U89) -> -808619.85 | N4: DATOS / Análisis y si
B6: TIR (5 años): | E6: =IRR(I28:I33) -> 0.87225097
B7: TIR (a perpetuidad): | E7: =IRR(I28:I34) -> 0.91050553
D8: VALOR PRESENTE NETO (en periodo de análisis): | E8: =J34 -> 947336.46
B9: PUNTO DE EQUILIBRIO AL AÑO: | E9: =K48 -> 2
B10: RETORNO DE LA INVERSIÓN AL AÑO: | E10: =K34 -> 1.1902474
B12: VALUACIÓN POR FLUJOS DESCONTADOS
B13: VALOR BRUTO DE LA EMPRESA (Enterprise Value): | E13: =I34+J34 -> 2223870
D14: CAJA | E14: 0
D15: PASIVOS LABORABLES | E15: 0
D16: PASIVOS FINANCIEROS | E16: 0
B17: VALOR NETO DE LA EMPRESA (Equity Value): | E17: =E13+E14-E15-E16 -> 2223870
B18: Inversión / Valor Neto (% de la empresa): | E18: =-E4/E17 -> 0.36360932
B20: VALUACIÓN POR MÚLTIPLOS
E21: 8.8548382
B22: MÚLTIPLOS EBIT (a valor presente): | E22: =((MEDIAN('Presupuesto Anual'!Q69:U69)*E21)/(1+'Costo de Capital'!C28)^B33) -> 2223870
B23: Inversión / Valuación (% de la empresa): | E23: =(-E4/E22) -> 0.36360931
B27: AÑO | C27: INVERSIÓN INICIAL | D27: UTILIDAD DE OPERACIÓN (EBIT) | E27: NOPAT | F27: + D&A | G27: +/- VAR. EN EL CAP. DE TRABAJO | H27: +/- INVERSIÓN DE ACTIVO FIJO (CAPEX) | I27: Flujo c/ Valor Terminal | J27: VPN | K27: DPBP (Discount Payback Period) Efectivo
B28: 0 | C28: =-E4 -> 808619.85 | I28: =-C28 -> -808619.85 | J28: =I28 -> -808619.85 | K28: =J28 -> -808619.85 | L28: 0
B29: 1 | D29: ='Presupuesto Anual'!Q69 -> 757591.62 | E29: =D29 -> 757591.62 | F29: ='Presupuesto Anual'!Q62+'Presupuesto Anual'!Q67 -> 132858.33 | G29: =F64 -> -39894.794 | H29: 0 | I29: =SUM(E29:H29) -> 850555.16 | J29: =I29/(1+'Costo de Capital'!$C$28)^B29 -> 682026.43 | K29: =K28+J29 -> -126593.42 | L29: 1
B30: 2 | D30: ='Presupuesto Anual'!R69 -> 1677570.7 | E30: =D30-IF(D30>0,D30*(SUPUESTOS!$D$3+SUPUESTOS!$D$4),0) -> 1006542.4 | F30: ='Presupuesto Anual'!R62+'Presupuesto Anual'!R67 -> 40700 | G30: =F65 -> -12350.672 | H30: 0 | I30: =SUM(E30:H30) -> 1034891.7 | J30: =I30/(1+'Costo de Capital'!$C$28)^B30 -> 665414.66 | K30: =K29+J30 -> 538821.24 | L30: 2
B31: 3 | D31: ='Presupuesto Anual'!S69 -> -98795.704 | E31: =D31-IF(D31>0,D31*(SUPUESTOS!$D$3+SUPUESTOS!$D$4),0) -> -98795.704 | F31: ='Presupuesto Anual'!S62+'Presupuesto Anual'!S67 -> 40700 | G31: =F66 -> -13504.024 | H31: 0 | I31: =SUM(E31:H31) -> -71599.728 | J31: =I31/(1+'Costo de Capital'!$C$28)^B31 -> -36915.396 | K31: =K30+J31 -> 501905.84 | L31: 3
B32: 4 | D32: ='Presupuesto Anual'!T69 -> 666002.48 | E32: =D32-IF(D32>0,D32*(SUPUESTOS!$D$3+SUPUESTOS!$D$4),0) -> 399601.49 | F32: ='Presupuesto Anual'!T62+'Presupuesto Anual'!T67 -> 40700 | G32: =F67 -> -13699.678 | H32: 0 | I32: =SUM(E32:H32) -> 426601.81 | J32: =I32/(1+'Costo de Capital'!$C$28)^B32 -> 176367.1 | K32: =K31+J32 -> 678272.94 | L32: 4
B33: 5 | D33: ='Presupuesto Anual'!U69 -> 1305846 | E33: =D33-IF(D33>0,D33*(SUPUESTOS!$D$3+SUPUESTOS!$D$4),0) -> 783507.58 | F33: ='Presupuesto Anual'!U62+'Presupuesto Anual'!U67 -> 40700 | G33: =F68 -> -12571.751 | H33: 0 | I33: =SUM(E33:H33) -> 811635.83 | J33: =I33/(1+'Costo de Capital'!$C$28)^B33 -> 269063.52 | K33: =K32+J33 -> 947336.46 | L33: 5
H34: Perpetuidad: | I34: =J56 -> 1276533.5 | J34: =SUM(J28:J33) -> 947336.46 | K34: =K37+ABS(K38)/K39 -> 1.1902474
J35: =NPV('Costo de Capital'!C28,I29:I33)+I28 -> 947336.46
J37: ULTIMO PERIODO EN NEGATIVO | K37: =SUMPRODUCT(--(K29:K33<0)) -> 1
J38: ULTIMA CANTIDAD NEGATIVA (+) | K38: =IFERROR(INDEX(K29:K33,K37),0) -> -126593.42
J39: PRIMER FLUJO DE EFECTIVO POSITIVO | K39: =IFERROR(INDEX(J29:J33,K37+1),J33) -> 665414.66
K41: BREAK EVEN POINT
K42: ='Presupuesto Anual'!Q69 -> 757591.62 | L42: 1
K43: ='Presupuesto Anual'!R69 -> 1677570.7 | L43: 2
K44: ='Presupuesto Anual'!S69 -> -98795.704 | L44: 3
K45: ='Presupuesto Anual'!T69 -> 666002.48 | L45: 4
K46: ='Presupuesto Anual'!U69 -> 1305846 | L46: 5
J48: ULTIMO PERIODO EN NEGATIVO | K48: =SUMPRODUCT(--(K42:K46<0))+1 -> 2
J49: ULTIMA CANTIDAD NEGATIVA (+) | K49: =IFERROR(INDEX(K42:K46,SUMPRODUCT(--(K42:K46<0))),0) -> 757591.62
I52: Tasa de crecimiento de la Perpetuidad | J52: =SUPUESTOS!D8 -> 0.03
I53: Siguiente flujo con Tasa de crecimiento de la Perpetuidad | J53: =I33*(1+J52) -> 835984.91
I54: Tasa de Perpetuidad | J54: ='Costo de Capital'!C28-J52 -> 0.2171
I55: VALOR TERMINAL (PERPETUIDAD) | J55: =J53/J54 -> 3850690.5
I56: VALOR TERMINAL (PERPETUIDAD) A VP | J56: =J55/(1+'Costo de Capital'!C28)^B33 -> 1276533.5
B62: AÑO | C62: CXC | D62: INVENTARIOS | E62: CXP | F62: VAR. CAP. TRABAJO | G62: CAP. TRABAJO NETO | H62: SUPUESTOS DE CAPITAL DE TRABAJO
B63: 0 | C63: 0 | D63: 0 | E63: 0 | F63: 0 | G63: 0 | I63: Días Cartera (DSO) | J63: 30
B64: 1 | C64: =('Presupuesto Anual'!Q18*$J$64)*$J$63/$J$67 -> 32375 | D64: =(SUM('Presupuesto Anual'!Q23:Q31)*$J$65/$J$67) -> 30079.175 | E64: =SUM('Presupuesto Anual'!Q23:Q31)*$J$66/$J$67 -> 22559.381 | F64: =-(G64-G63) -> -39894.794 | G64: =C64+D64-E64 -> 39894.794 | I64: Clientes con Crédito | J64: 0.1
B65: 2 | C65: =('Presupuesto Anual'!R18*J64)*$J$63/$J$67 -> 42127.583 | D65: =SUM('Presupuesto Anual'!R23:R31)*$J$65/$J$67 -> 40471.53 | E65: =SUM('Presupuesto Anual'!R23:R31)*$J$66/$J$67 -> 30353.647 | F65: =-(G65-G64) -> -12350.672 | G65: =C65+D65-E65 -> 52245.466 | I65: Días Inventario (DIO) | J65: 60
B66: 3 | C66: =('Presupuesto Anual'!S18*J64)*$J$63/$J$67 -> 52659.479 | D66: =SUM('Presupuesto Anual'!S23:S31)*$J$65/$J$67 -> 52360.042 | E66: =SUM('Presupuesto Anual'!S23:S31)*$J$66/$J$67 -> 39270.031 | F66: =-(G66-G65) -> -13504.024 | G66: =C66+D66-E66 -> 65749.49 | I66: Días Proveedores (DPO) | J66: 45
B67: 4 | C67: =('Presupuesto Anual'!T18*J64)*$J$63/$J$67 -> 63191.375 | D67: =SUM('Presupuesto Anual'!T23:T31)*$J$65/$J$67 -> 65031.172 | E67: =SUM('Presupuesto Anual'!T23:T31)*$J$66/$J$67 -> 48773.379 | F67: =-(G67-G66) -> -13699.678 | G67: =C67+D67-E67 -> 79449.168 | I67: Días base (año) | J67: 360
B68: 5 | C68: =('Presupuesto Anual'!U18*J64)*$J$63/$J$67 -> 72670.081 | D68: =SUM('Presupuesto Anual'!U23:U31)*$J$65/$J$67 -> 77403.353 | E68: =SUM('Presupuesto Anual'!U23:U31)*$J$66/$J$67 -> 58052.514 | F68: =-(G68-G67) -> -12571.751 | G68: =C68+D68-E68 -> 92020.919

Sheet Costo de Capital
B2: CALCULO DE COSTO DE CAPITAL
D3: Observaciones
B4: Tasa libre de Riesgo Prom esperado a 10 años | C4: 0.08724 | D4: Bono 10 años SEP 2025
B5: Beta | C5: 1.2 | D5: Unlevered beta Apparel/Footwear (Damodaran, ene-2026)
B6: Prima de Riesgo de Mercado (ERP madura) | C6: 0.0433 | D6: ERP implicita S&P 500 (Damodaran, 2025)
B7: Empresa pequeña | C7: 0 | D7: Conocimiento especializado y data analytics con valor futuro en el mercado
B8: Startup | C8: 0.05 | D8: Premio por Startup
B9: TOTAL PREMIO RIESGO | C9: =C7+C8 -> 0.05
B11: Country risk premium | C11: 0.0379
B12: Convencionalismo | C12: 0.02
B14: Costo de Capital Nominal (CAPM-N) | C14: =C4+C5*C6+C9+C11+C12 -> 0.2471
B15: Inflación | C15: =SUPUESTOS!D6 -> 0.035
B16: Costo de Capital Real (CAPM) | C16: =+((1+C14)/(1+C15))-1 -> 0.20492754
B18: Costo de deuda nominal | C18: =+C19*(1-C20) -> 0.105
B19: Costo de deuda antes de imptos | C19: ='Crédito Bancario'!D4 -> 0.15 | D19: TIIE + 3.5
B20: Tasa de impuestos | C20: =SUPUESTOS!D3 -> 0.3 | D20: Tasa ISR
B21: Inflación | C21: =SUPUESTOS!D6 -> 0.035 | D21: =D15 -> 0
B22: Costo de deuda real | C22: =+((1+C18)/(1+C21))-1 -> 0.06763285
B24: Proporcion de capital | C24: 1
B26: Proporción de deuda | C26: 0
B28: WACC nominal | C28: =+(C14*C24)+(C18*C26) -> 0.2471
B29: WACC real | C29: =+(C16*C24)+(C22*C26) -> 0.20492754
B31: IPC en los últimos años
B32: 37226 | C32: 6372
B33: 37591 | C33: 6127 | D33: =C33/C32-1 -> -0.038449466
B34: 37956 | C34: 8795 | D34: =C34/C33-1 -> 0.43544965
B35: 38322 | C35: 12918 | D35: =C35/C34-1 -> 0.46878908
B36: 38687 | C36: 17803 | D36: =C36/C35-1 -> 0.37815451
B37: 39052 | C37: 26448 | D37: =C37/C36-1 -> 0.48559232
B38: 39417 | C38: 29537 | D38: =C38/C37-1 -> 0.11679522
B39: 39783 | C39: 22380 | D39: =C39/C38-1 -> -0.24230626
B40: 40148 | C40: 32120 | D40: =C40/C39-1 -> 0.43521001
B41: 40513 | C41: 38551 | D41: =C41/C40-1 -> 0.20021793
B42: 40878 | C42: 37078 | D42: =C42/C41-1 -> -0.038209126
B43: 41244 | C43: 43706 | D43: =+C43/C42-1 -> 0.17875829
B44: 41609 | C44: 42727 | D44: =+C44/C43-1 -> -0.022399671
B45: 41974 | C45: 43146 | D45: =+C45/C44-1 -> 0.0098064456
B46: 42339 | C46: 42978 | D46: =+C46/C45-1 -> -0.0038937561
B47: 42705 | C47: 45643 | D47: =+C47/C46-1 -> 0.062008469
B48: 43070 | C48: 49354 | D48: =+C48/C47-1 -> 0.08130491
B49: 43465 | C49: 41640 | D49: =+C49/C48-1 -> -0.15629939
B50: 43830 | C50: 43541 | D50: =+C50/C49-1 -> 0.045653218
B51: 44196 | C51: 44067 | D51: =+C51/C50-1 -> 0.012080568
B52: 44531 | C52: 53272 | D52: =+C52/C51-1 -> 0.20888647
B53: 44896 | C53: 48464 | D53: =+C53/C52-1 -> -0.090253792
B54: 45261 | C54: 57386 | D54: =+C54/C53-1 -> 0.18409541
... B56: 45992 | C56: 64308 | D56: =+C56/C55-1 -> 0.29881041
B57: Promedio Últimos 20 años | D57: =AVERAGE(D37:D56) -> 0.081433197
B58: Promedio Últimos 15 años | D58: =AVERAGE(D42:D56) -> 0.042210315
B59: Promedio Últimos 10 años | D59: =AVERAGE(D47:D56) -> 0.050909254
B61: REFERENCIAS:
B62: http://www.banxico.org.mx/SieInternet/consultarDirectorioInternetAction.do?accion=consultarCuadro&idCuadro=CF107&sector=22&locale=es
B63: http://www.banxico.org.mx/portal-inflacion/inflacion.html
B64: http://finance.yahoo.com/q/hp?s=%5EMXX+Historical+Prices
B65: http://eleconomista.com.mx/mercados-estadisticas/2014/05/22/mejora-pronostico-ipc
B66: https://mx.investing.com/rates-bonds/mexico-10-year

Sheet SUPUESTOS
B3: Tasa de Impuestos | D3: 0.3
B4: PTU | D4: 0.1
B6: INFLACIÓN | D6: 0.035
B8: Crecimiento anual | D8: 0.03
